LICENSE
MANIFEST.in
README.rst
requirements.txt
setup.py
pyhdust/__init__.py
pyhdust/basoptics.py
pyhdust/bcd.py
pyhdust/beatlas.py
pyhdust/fieldstars.py
pyhdust/hdrpil.py
pyhdust/images.py
pyhdust/input.py
pyhdust/interftools.py
pyhdust/jdcal.py
pyhdust/oifits.py
pyhdust/phc.py
pyhdust/poltools.py
pyhdust/releases.py
pyhdust/rotstars.py
pyhdust/singscat.py
pyhdust/spectools.py
pyhdust/stats.py
pyhdust/tabulate.py
pyhdust/triangle.py
pyhdust.egg-info/PKG-INFO
pyhdust.egg-info/SOURCES.txt
pyhdust.egg-info/dependency_links.txt
pyhdust.egg-info/not-zip-safe
pyhdust.egg-info/requires.txt
pyhdust.egg-info/top_level.txt
pyhdust/lrr/__init__.py
pyhdust/lrr/jdutil.py
pyhdust/lrr/roche_singlestar.py
pyhdust/refs/NIST_observ.xls
pyhdust/refs/REF.bat
pyhdust/refs/REF.bgp
pyhdust/refs/REF.bgq
pyhdust/refs/REF.ge
pyhdust/refs/REF.inp
pyhdust/refs/REF.job
pyhdust/refs/REF.oar
pyhdust/refs/REF.slurm
pyhdust/refs/REF.slurm_cl
pyhdust/refs/REF_bistabWind1Dust.txt
pyhdust/refs/REF_disco.txt
pyhdust/refs/REF_estrela.txt
pyhdust/refs/REF_images.txt
pyhdust/refs/REF_inp.txt
pyhdust/refs/REF_simul.txt
pyhdust/refs/bcd_BA.txt
pyhdust/refs/dths.txt
pyhdust/refs/dths_stddevmean.txt
pyhdust/refs/fp00k0.pck
pyhdust/refs/geneve_par.pro
pyhdust/refs/obs_alvos.txt
pyhdust/refs/obs_dec.txt
pyhdust/refs/obs_ef.txt
pyhdust/refs/pol_alvos.txt
pyhdust/refs/pol_hip.txt
pyhdust/refs/pol_mags.txt
pyhdust/refs/pol_padroes.txt
pyhdust/refs/pol_unpol.txt
pyhdust/refs/rgb_eff.txt
pyhdust/refs/extern/bcd.ori.py2
pyhdust/refs/extern/jdutils.ori.py
pyhdust/refs/extern/oifits.ori.py2
pyhdust/refs/extern/oitools.py2
pyhdust/refs/extern/tabulate.ori.py
pyhdust/refs/filters/2MASS_2MASS.H.dat
pyhdust/refs/filters/2MASS_2MASS.J.dat
pyhdust/refs/filters/2MASS_2MASS.Ks.dat
pyhdust/refs/filters/AKARI_FIS.N160.dat
pyhdust/refs/filters/AKARI_FIS.N60.dat
pyhdust/refs/filters/AKARI_FIS.WIDE-L.dat
pyhdust/refs/filters/AKARI_FIS.WIDE-S.dat
pyhdust/refs/filters/APEX-LABOCA.dat
pyhdust/refs/filters/B.dat
pyhdust/refs/filters/Bessell_B.dat
pyhdust/refs/filters/Bessell_H.dat
pyhdust/refs/filters/Bessell_I.dat
pyhdust/refs/filters/Bessell_J.dat
pyhdust/refs/filters/Bessell_K.dat
