Metadata-Version: 2.1
Name: pyhdust
Version: 1.6.0
Summary: Analysis tools for multi-technique astronomical data and hdust models
Home-page: http://pyhdust.readthedocs.io
Author: Daniel M. Faes
Author-email: dmfaes@gmail.com
License: GNU GPLv3.0
Keywords: astronomy,astrophysics,science,hdust,Be stars,spectroscopy,polarimetry,interferometry,radiative transfer,optical-interferometry
Classifier: Development Status :: 5 - Production/Stable
Classifier: Intended Audience :: Developers
Classifier: Intended Audience :: Science/Research
Classifier: License :: OSI Approved :: GNU General Public License v3 or later (GPLv3+)
Classifier: Operating System :: OS Independent
Classifier: Programming Language :: Python
Classifier: Programming Language :: Python :: 3
Classifier: Topic :: Scientific/Engineering :: Astronomy
Classifier: Topic :: Scientific/Engineering :: Physics
Requires-Python: >=3.6
License-File: LICENSE
Requires-Dist: numpy
Requires-Dist: six
Requires-Dist: astropy
Requires-Dist: python-dateutil
Requires-Dist: sphinx-rtd-theme
